Metadata-Version: 2.1
Name: django-seohelper
Version: 1.0.0
Summary: Manager the meta information of your pages in Django
Home-page: https://github.com/kplaube/django-seohelper/
Author: Klaus Laube
Author-email: kplaube@gmail.com
License: GNU Lesser General Public License (LGPL), Version 3
Keywords: web django apps seo seohelper
Platform: UNKNOWN
Classifier: Environment :: Plugins
Classifier: Framework :: Django
Classifier: Intended Audience :: Developers
Classifier: License :: OSI Approved :: GNU Library or Lesser General Public License (LGPL)
Classifier: Operating System :: OS Independent
Classifier: Programming Language :: Python
Classifier: Topic :: Software Development :: Libraries :: Python Modules
